Metadata-Version: 2.1
Name: changelogs
Version: 0.15.0
Summary: A changelog finder and parser.
Home-page: https://github.com/pyupio/changelogs
Author: pyup.io
Author-email: support@pyup.io
License: MIT license
Keywords: changelogs
Platform: UNKNOWN
Classifier: Development Status :: 2 - Pre-Alpha
Classifier: Intended Audience :: Developers
Classifier: License :: OSI Approved :: MIT License
Classifier: Natural Language :: English
Classifier: Programming Language :: Python :: 3
Classifier: Programming Language :: Python :: 3.6
Classifier: Programming Language :: Python :: 3.7
Classifier: Programming Language :: Python :: 3.8
Requires-Dist: requests
Requires-Dist: validators
Requires-Dist: packaging
Requires-Dist: lxml
Requires-Dist: gitchangelog
Provides-Extra: dev
Requires-Dist: mock ; extra == 'dev'
Requires-Dist: pytest ; extra == 'dev'
Requires-Dist: pytest-cov ; extra == 'dev'
Requires-Dist: betamax ; extra == 'dev'
Requires-Dist: betamax-serializers ; extra == 'dev'
Requires-Dist: flake8 ; extra == 'dev'
Requires-Dist: tox ; extra == 'dev'
Provides-Extra: test
Requires-Dist: mock ; extra == 'test'
Requires-Dist: pytest ; extra == 'test'
Requires-Dist: pytest-cov ; extra == 'test'
Requires-Dist: betamax ; extra == 'test'
Requires-Dist: betamax-serializers ; extra == 'test'
